setup.py
MIDAS/MIDAS.py
MIDAS_V.egg-info/PKG-INFO
MIDAS_V.egg-info/SOURCES.txt
MIDAS_V.egg-info/dependency_links.txt
MIDAS_V.egg-info/top_level.txt