Metadata-Version: 1.0
Name: MIDAS-V
Version: 1.0
Summary: MIDAS is a system for generating Boolean Framework for Modeling and Inferring Drug Targets and Drug Resistance Mechanisms
Home-page: https://github.com/vrushali-broad/MIDAS/tree/master
Author: Vrushali Dipak Fangal, Amitabh Sharma, Channing Division of Network Medicine, Harvard Medical School
Author-email: vrushali@broadinstitute.org
License: MIT
Platform: UNKNOWN
